agrimetscraper/__init__.py
agrimetscraper/__main__.py
agrimetscraper/coretools/__init__.py
agrimetscraper/coretools/crawler.py
agrimetscraper/coretools/dataprocess.py
agrimetscraper/coretools/urlbuilder.py
agrimetscraper/scheduler/__init__.py
agrimetscraper/scheduler/scheduler.py
agrimetscraper/template/__init__.py
agrimetscraper/template/pipeline.py
agrimetscraper/template/runproject.py
agrimetscraper/utils/__init__.py
agrimetscraper/utils/configreader.py
agrimetscraper/utils/configurations.py
agrimetscraper/utils/converters.py
agrimetscraper/utils/dbwrite.py
agrimetscraper/utils/duplicatechecker.py
agrimetscraper/utils/helpertools.py
agrimetscraper/utils/instantData_aggregate.py
agrimetscraper/utils/mongoDB.py
agrimetscraper/utils/mongoSetup.py
agrimetscraper/utils/mylogger.py
agrimetscraper/utils/requestformatter.py
agrimetscraper/utils/stationinfo.py
agrimetscraper-0.4.2.data/scripts/startproject.py
agrimetscraper-0.4.2.dist-info/LICENSE
agrimetscraper-0.4.2.dist-info/METADATA
agrimetscraper-0.4.2.dist-info/WHEEL
agrimetscraper-0.4.2.dist-info/top_level.txt
agrimetscraper-0.4.2.dist-info/RECORD
