Metadata-Version: 2.1
Name: agrimetscraper
Version: 0.4.2
Summary: A package to scrape AgriMet weather data
Home-page: https://github.com/lixiaopi1985/agrimet_scraper
Author: Xiaoping Li
Author-email: lixiaopi@oregonstate.edu
License: UNKNOWN
Platform: UNKNOWN
Classifier: Programming Language :: Python :: 3
Classifier: License :: OSI Approved :: MIT License
Classifier: Operating System :: OS Independent
Requires-Dist: pandas
Requires-Dist: numpy
Requires-Dist: python-crontab
Requires-Dist: requests
Requires-Dist: fake-useragent
Requires-Dist: bs4
Requires-Dist: pymongo
Requires-Dist: dnspython
